<annotation>
	<folder>JPEGImages</folder>
	<filename>23.jpg</filename>
	<path>C:\Users\space\Desktop\VOC2007\JPEGImages\23.jpg</path>
	<source>
		<database>Unknown</database>
	</source>
	<size>
		<width>3648</width>
		<height>2736</height>
		<depth>3</depth>
	</size>
	<segmented>0</segmented>
	<object>
		<name>pith</name>
		<pose>Unspecified</pose>
		<truncated>0</truncated>
		<difficult>0</difficult>
		<bndbox>
			<xmin>16</xmin>
			<ymin>41</ymin>
			<xmax>140</xmax>
			<ymax>273</ymax>
		</bndbox>
	</object>
	<object>
		<name>pith</name>
		<pose>Unspecified</pose>
		<truncated>0</truncated>
		<difficult>0</difficult>
		<bndbox>
			<xmin>460</xmin>
			<ymin>606</ymin>
			<xmax>625</xmax>
			<ymax>782</ymax>
		</bndbox>
	</object>
	<object>
		<name>pith</name>
		<pose>Unspecified</pose>
		<truncated>0</truncated>
		<difficult>0</difficult>
		<bndbox>
			<xmin>60</xmin>
			<ymin>885</ymin>
			<xmax>257</xmax>
			<ymax>1094</ymax>
		</bndbox>
	</object>
	<object>
		<name>pith</name>
		<pose>Unspecified</pose>
		<truncated>0</truncated>
		<difficult>0</difficult>
		<bndbox>
			<xmin>49</xmin>
			<ymin>1547</ymin>
			<xmax>260</xmax>
			<ymax>1712</ymax>
		</bndbox>
	</object>
	<object>
		<name>pith</name>
		<pose>Unspecified</pose>
		<truncated>0</truncated>
		<difficult>0</difficult>
		<bndbox>
			<xmin>369</xmin>
			<ymin>1494</ymin>
			<xmax>625</xmax>
			<ymax>1712</ymax>
		</bndbox>
	</object>
	<object>
		<name>pith</name>
		<pose>Unspecified</pose>
		<truncated>0</truncated>
		<difficult>0</difficult>
		<bndbox>
			<xmin>710</xmin>
			<ymin>1579</ymin>
			<xmax>896</xmax>
			<ymax>1785</ymax>
		</bndbox>
	</object>
	<object>
		<name>pith</name>
		<pose>Unspecified</pose>
		<truncated>0</truncated>
		<difficult>0</difficult>
		<bndbox>
			<xmin>949</xmin>
			<ymin>2264</ymin>
			<xmax>1154</xmax>
			<ymax>2459</ymax>
		</bndbox>
	</object>
	<object>
		<name>pith</name>
		<pose>Unspecified</pose>
		<truncated>0</truncated>
		<difficult>0</difficult>
		<bndbox>
			<xmin>1554</xmin>
			<ymin>967</ymin>
			<xmax>1740</xmax>
			<ymax>1167</ymax>
		</bndbox>
	</object>
	<object>
		<name>pith</name>
		<pose>Unspecified</pose>
		<truncated>1</truncated>
		<difficult>0</difficult>
		<bndbox>
			<xmin>1781</xmin>
			<ymin>1</ymin>
			<xmax>1890</xmax>
			<ymax>162</ymax>
		</bndbox>
	</object>
	<object>
		<name>pith</name>
		<pose>Unspecified</pose>
		<truncated>0</truncated>
		<difficult>0</difficult>
		<bndbox>
			<xmin>2499</xmin>
			<ymin>2447</ymin>
			<xmax>2746</xmax>
			<ymax>2659</ymax>
		</bndbox>
	</object>
	<object>
		<name>pith</name>
		<pose>Unspecified</pose>
		<truncated>0</truncated>
		<difficult>0</difficult>
		<bndbox>
			<xmin>3125</xmin>
			<ymin>1497</ymin>
			<xmax>3340</xmax>
			<ymax>1759</ymax>
		</bndbox>
	</object>
	<object>
		<name>pith</name>
		<pose>Unspecified</pose>
		<truncated>0</truncated>
		<difficult>0</difficult>
		<bndbox>
			<xmin>3222</xmin>
			<ymin>756</ymin>
			<xmax>3399</xmax>
			<ymax>1014</ymax>
		</bndbox>
	</object>
	<object>
		<name>pith</name>
		<pose>Unspecified</pose>
		<truncated>0</truncated>
		<difficult>0</difficult>
		<bndbox>
			<xmin>2922</xmin>
			<ymin>914</ymin>
			<xmax>3119</xmax>
			<ymax>1159</ymax>
		</bndbox>
	</object>
	<object>
		<name>pith</name>
		<pose>Unspecified</pose>
		<truncated>0</truncated>
		<difficult>0</difficult>
		<bndbox>
			<xmin>2569</xmin>
			<ymin>1370</ymin>
			<xmax>2813</xmax>
			<ymax>1573</ymax>
		</bndbox>
	</object>
	<object>
		<name>pith</name>
		<pose>Unspecified</pose>
		<truncated>0</truncated>
		<difficult>0</difficult>
		<bndbox>
			<xmin>2363</xmin>
			<ymin>1459</ymin>
			<xmax>2557</xmax>
			<ymax>1732</ymax>
		</bndbox>
	</object>
	<object>
		<name>pith</name>
		<pose>Unspecified</pose>
		<truncated>1</truncated>
		<difficult>0</difficult>
		<bndbox>
			<xmin>2790</xmin>
			<ymin>1</ymin>
			<xmax>2999</xmax>
			<ymax>141</ymax>
		</bndbox>
	</object>
	<object>
		<name>pith</name>
		<pose>Unspecified</pose>
		<truncated>0</truncated>
		<difficult>0</difficult>
		<bndbox>
			<xmin>2702</xmin>
			<ymin>159</ymin>
			<xmax>2819</xmax>
			<ymax>423</ymax>
		</bndbox>
	</object>
	<object>
		<name>pith</name>
		<pose>Unspecified</pose>
		<truncated>0</truncated>
		<difficult>0</difficult>
		<bndbox>
			<xmin>2852</xmin>
			<ymin>170</ymin>
			<xmax>3090</xmax>
			<ymax>388</ymax>
		</bndbox>
	</object>
	<object>
		<name>pith</name>
		<pose>Unspecified</pose>
		<truncated>0</truncated>
		<difficult>0</difficult>
		<bndbox>
			<xmin>628</xmin>
			<ymin>2394</ymin>
			<xmax>843</xmax>
			<ymax>2564</ymax>
		</bndbox>
	</object>
	<object>
		<name>pith</name>
		<pose>Unspecified</pose>
		<truncated>0</truncated>
		<difficult>0</difficult>
		<bndbox>
			<xmin>1943</xmin>
			<ymin>1456</ymin>
			<xmax>2075</xmax>
			<ymax>1626</ymax>
		</bndbox>
	</object>
</annotation>
