<annotation>
	<folder>JPEGImages</folder>
	<filename>302.jpg</filename>
	<path>C:\Users\space\Desktop\VOC2007\JPEGImages\302.jpg</path>
	<source>
		<database>Unknown</database>
	</source>
	<size>
		<width>3648</width>
		<height>2736</height>
		<depth>3</depth>
	</size>
	<segmented>0</segmented>
	<object>
		<name>pith</name>
		<pose>Unspecified</pose>
		<truncated>0</truncated>
		<difficult>0</difficult>
		<bndbox>
			<xmin>2115</xmin>
			<ymin>876</ymin>
			<xmax>2288</xmax>
			<ymax>1012</ymax>
		</bndbox>
	</object>
	<object>
		<name>pith</name>
		<pose>Unspecified</pose>
		<truncated>0</truncated>
		<difficult>0</difficult>
		<bndbox>
			<xmin>1765</xmin>
			<ymin>1997</ymin>
			<xmax>1935</xmax>
			<ymax>2164</ymax>
		</bndbox>
	</object>
	<object>
		<name>pith</name>
		<pose>Unspecified</pose>
		<truncated>0</truncated>
		<difficult>0</difficult>
		<bndbox>
			<xmin>600</xmin>
			<ymin>1606</ymin>
			<xmax>762</xmax>
			<ymax>1779</ymax>
		</bndbox>
	</object>
	<object>
		<name>pith</name>
		<pose>Unspecified</pose>
		<truncated>0</truncated>
		<difficult>0</difficult>
		<bndbox>
			<xmin>174</xmin>
			<ymin>1544</ymin>
			<xmax>262</xmax>
			<ymax>1747</ymax>
		</bndbox>
	</object>
	<object>
		<name>pith</name>
		<pose>Unspecified</pose>
		<truncated>0</truncated>
		<difficult>0</difficult>
		<bndbox>
			<xmin>29</xmin>
			<ymin>2256</ymin>
			<xmax>194</xmax>
			<ymax>2420</ymax>
		</bndbox>
	</object>
	<object>
		<name>pith</name>
		<pose>Unspecified</pose>
		<truncated>0</truncated>
		<difficult>0</difficult>
		<bndbox>
			<xmin>285</xmin>
			<ymin>326</ymin>
			<xmax>406</xmax>
			<ymax>470</ymax>
		</bndbox>
	</object>
	<object>
		<name>pith</name>
		<pose>Unspecified</pose>
		<truncated>0</truncated>
		<difficult>0</difficult>
		<bndbox>
			<xmin>82</xmin>
			<ymin>917</ymin>
			<xmax>188</xmax>
			<ymax>1059</ymax>
		</bndbox>
	</object>
	<object>
		<name>pith</name>
		<pose>Unspecified</pose>
		<truncated>0</truncated>
		<difficult>0</difficult>
		<bndbox>
			<xmin>115</xmin>
			<ymin>1100</ymin>
			<xmax>212</xmax>
			<ymax>1217</ymax>
		</bndbox>
	</object>
	<object>
		<name>pith</name>
		<pose>Unspecified</pose>
		<truncated>0</truncated>
		<difficult>0</difficult>
		<bndbox>
			<xmin>908</xmin>
			<ymin>568</ymin>
			<xmax>1090</xmax>
			<ymax>765</ymax>
		</bndbox>
	</object>
	<object>
		<name>pith</name>
		<pose>Unspecified</pose>
		<truncated>0</truncated>
		<difficult>0</difficult>
		<bndbox>
			<xmin>1288</xmin>
			<ymin>370</ymin>
			<xmax>1450</xmax>
			<ymax>564</ymax>
		</bndbox>
	</object>
	<object>
		<name>pith</name>
		<pose>Unspecified</pose>
		<truncated>0</truncated>
		<difficult>0</difficult>
		<bndbox>
			<xmin>1185</xmin>
			<ymin>1388</ymin>
			<xmax>1356</xmax>
			<ymax>1676</ymax>
		</bndbox>
	</object>
	<object>
		<name>pith</name>
		<pose>Unspecified</pose>
		<truncated>0</truncated>
		<difficult>0</difficult>
		<bndbox>
			<xmin>2409</xmin>
			<ymin>591</ymin>
			<xmax>2544</xmax>
			<ymax>794</ymax>
		</bndbox>
	</object>
	<object>
		<name>pith</name>
		<pose>Unspecified</pose>
		<truncated>0</truncated>
		<difficult>0</difficult>
		<bndbox>
			<xmin>2585</xmin>
			<ymin>314</ymin>
			<xmax>2721</xmax>
			<ymax>500</ymax>
		</bndbox>
	</object>
	<object>
		<name>pith</name>
		<pose>Unspecified</pose>
		<truncated>0</truncated>
		<difficult>0</difficult>
		<bndbox>
			<xmin>3050</xmin>
			<ymin>79</ymin>
			<xmax>3147</xmax>
			<ymax>238</ymax>
		</bndbox>
	</object>
	<object>
		<name>pith</name>
		<pose>Unspecified</pose>
		<truncated>0</truncated>
		<difficult>0</difficult>
		<bndbox>
			<xmin>2176</xmin>
			<ymin>26</ymin>
			<xmax>2244</xmax>
			<ymax>156</ymax>
		</bndbox>
	</object>
	<object>
		<name>pith</name>
		<pose>Unspecified</pose>
		<truncated>0</truncated>
		<difficult>0</difficult>
		<bndbox>
			<xmin>2993</xmin>
			<ymin>564</ymin>
			<xmax>3146</xmax>
			<ymax>720</ymax>
		</bndbox>
	</object>
	<object>
		<name>pith</name>
		<pose>Unspecified</pose>
		<truncated>0</truncated>
		<difficult>0</difficult>
		<bndbox>
			<xmin>3194</xmin>
			<ymin>603</ymin>
			<xmax>3303</xmax>
			<ymax>797</ymax>
		</bndbox>
	</object>
	<object>
		<name>pith</name>
		<pose>Unspecified</pose>
		<truncated>0</truncated>
		<difficult>0</difficult>
		<bndbox>
			<xmin>2906</xmin>
			<ymin>797</ymin>
			<xmax>3035</xmax>
			<ymax>923</ymax>
		</bndbox>
	</object>
	<object>
		<name>pith</name>
		<pose>Unspecified</pose>
		<truncated>0</truncated>
		<difficult>0</difficult>
		<bndbox>
			<xmin>3194</xmin>
			<ymin>1056</ymin>
			<xmax>3341</xmax>
			<ymax>1194</ymax>
		</bndbox>
	</object>
	<object>
		<name>pith</name>
		<pose>Unspecified</pose>
		<truncated>1</truncated>
		<difficult>0</difficult>
		<bndbox>
			<xmin>3579</xmin>
			<ymin>223</ymin>
			<xmax>3648</xmax>
			<ymax>414</ymax>
		</bndbox>
	</object>
	<object>
		<name>pith</name>
		<pose>Unspecified</pose>
		<truncated>1</truncated>
		<difficult>0</difficult>
		<bndbox>
			<xmin>3500</xmin>
			<ymin>1106</ymin>
			<xmax>3648</xmax>
			<ymax>1220</ymax>
		</bndbox>
	</object>
	<object>
		<name>pith</name>
		<pose>Unspecified</pose>
		<truncated>0</truncated>
		<difficult>0</difficult>
		<bndbox>
			<xmin>2997</xmin>
			<ymin>1712</ymin>
			<xmax>3106</xmax>
			<ymax>1885</ymax>
		</bndbox>
	</object>
	<object>
		<name>pith</name>
		<pose>Unspecified</pose>
		<truncated>0</truncated>
		<difficult>0</difficult>
		<bndbox>
			<xmin>3021</xmin>
			<ymin>2194</ymin>
			<xmax>3121</xmax>
			<ymax>2317</ymax>
		</bndbox>
	</object>
	<object>
		<name>pith</name>
		<pose>Unspecified</pose>
		<truncated>0</truncated>
		<difficult>0</difficult>
		<bndbox>
			<xmin>2432</xmin>
			<ymin>1912</ymin>
			<xmax>2541</xmax>
			<ymax>2032</ymax>
		</bndbox>
	</object>
	<object>
		<name>pith</name>
		<pose>Unspecified</pose>
		<truncated>0</truncated>
		<difficult>0</difficult>
		<bndbox>
			<xmin>1821</xmin>
			<ymin>1129</ymin>
			<xmax>1935</xmax>
			<ymax>1256</ymax>
		</bndbox>
	</object>
</annotation>
